odoo8_addon_l10n_id_taxform_pph_21-8.0.1.0.0-py2.7-nspkg.pth
odoo8_addon_l10n_id_taxform_pph_21-8.0.1.0.0.dist-info/top_level.txt
odoo8_addon_l10n_id_taxform_pph_21-8.0.1.0.0.dist-info/WHEEL
odoo8_addon_l10n_id_taxform_pph_21-8.0.1.0.0.dist-info/RECORD
odoo8_addon_l10n_id_taxform_pph_21-8.0.1.0.0.dist-info/metadata.json
odoo8_addon_l10n_id_taxform_pph_21-8.0.1.0.0.dist-info/DESCRIPTION.rst
odoo8_addon_l10n_id_taxform_pph_21-8.0.1.0.0.dist-info/METADATA
odoo8_addon_l10n_id_taxform_pph_21-8.0.1.0.0.dist-info/namespace_packages.txt
odoo_addons/l10n_id_taxform_pph_21/__openerp__.py
odoo_addons/l10n_id_taxform_pph_21/__init__.py
odoo_addons/l10n_id_taxform_pph_21/README.rst
odoo_addons/l10n_id_taxform_pph_21/security/ir.model.access.csv
odoo_addons/l10n_id_taxform_pph_21/models/pph_21_biaya_jabatan.py
odoo_addons/l10n_id_taxform_pph_21/models/pph_21_npwp_rate_modifier.py
odoo_addons/l10n_id_taxform_pph_21/models/pph_21_rate.py
odoo_addons/l10n_id_taxform_pph_21/models/res_partner.py
odoo_addons/l10n_id_taxform_pph_21/models/ptkp.py
odoo_addons/l10n_id_taxform_pph_21/models/__init__.py
odoo_addons/l10n_id_taxform_pph_21/views/res_partner_views.xml
odoo_addons/l10n_id_taxform_pph_21/views/pph_21_biaya_jabatan_views.xml
odoo_addons/l10n_id_taxform_pph_21/views/ptkp_views.xml
odoo_addons/l10n_id_taxform_pph_21/views/pph_21_npwp_rate_modifier_views.xml
odoo_addons/l10n_id_taxform_pph_21/views/pph_21_rate_views.xml
odoo_addons/l10n_id_taxform_pph_21/data/ptkp_category_data.xml
odoo_addons/l10n_id_taxform_pph_21/tests/test_biaya_jabatan.py
odoo_addons/l10n_id_taxform_pph_21/tests/test_pph_rate.py
odoo_addons/l10n_id_taxform_pph_21/tests/test_partner_pph_21.py
odoo_addons/l10n_id_taxform_pph_21/tests/__init__.py
odoo_addons/l10n_id_taxform_pph_21/tests/test_ptkp.py
odoo_addons/l10n_id_taxform_pph_21/demo/ptkp_demo.xml
odoo_addons/l10n_id_taxform_pph_21/demo/pph_21_rate_demo.xml
odoo_addons/l10n_id_taxform_pph_21/demo/pph_21_biaya_jabatan_demo.xml
odoo_addons/l10n_id_taxform_pph_21/demo/pph_21_npwp_rate_modifier_demo.xml
odoo_addons/l10n_id_taxform_pph_21/static/description/icon.png
