Metadata-Version: 2.0
Name: odoo8-addon-l10n-id-taxform-pph-21
Version: 8.0.1.0.0
Summary: Indonesia's PPh 21 Taxform Related Configuration and Computation
Home-page: https://opensynergy-indonesia.com/
Author: OpenSynergy Indonesia,Odoo Community Association (OCA)
Author-email: support@odoo-community.org
License: AGPL-3
Platform: UNKNOWN
Requires-Dist: odoo (<9.0a,>=8.0a)
Requires-Dist: odoo8-addon-l10n-id-taxform
Classifier: Programming Language :: Python :: 2.7
Classifier: Framework :: Odoo
Classifier: License :: OSI Approved :: GNU Affero General Public License v3
